modputs/__init__.py
modputs-0.0.6.dist-info/LICENSE.txt
modputs-0.0.6.dist-info/METADATA
modputs-0.0.6.dist-info/WHEEL
modputs-0.0.6.dist-info/top_level.txt
modputs-0.0.6.dist-info/RECORD
